klowd/__init__.py
klowd/__version__.py
klowd/core.py
klowd/float_item.py
klowd/wave_item.py
klowd-0.0.29.dist-info/METADATA
klowd-0.0.29.dist-info/WHEEL
klowd-0.0.29.dist-info/entry_points.txt
klowd-0.0.29.dist-info/top_level.txt
klowd-0.0.29.dist-info/RECORD
